{
  "results": [
    {
      "q": "VW",
      "items": [],
      "more": 0
    },
    {
      "q": "SVW",
      "items": [],
      "more": 0
    },
    {
      "q": "APP",
      "items": [],
      "more": 0
    },
    {
      "q": "TRK",
      "items": [
        {
          "key": "org.sonarsource:sonarqube",
          "name": "SonarSource :: SonarQube",
          "match": "<mark>Sonar</mark>Source :: <mark>Sonar</mark>Qube",
          "project": "",
          "isRecentlyBrowsed": true,
          "isFavorite": false
        },
        {
          "key": "org.sonarsource:sonarlint",
          "name": "SonarSource :: SonarLint",
          "match": "<mark>Sonar</mark>Source :: <mark>Sonar</mark>Lint",
          "project": "",
          "isRecentlyBrowsed": false,
          "isFavorite": false
        }
      ],
      "more": 0
    }
  ],
  "projects": [
  ]
}
