{
  "suggestions": [
    {
      "category": "projects",
      "items": [
        {
          "organization": "default-organization",
          "key": "org.sonarsource:sonarqube",
          "name": "SonarSource :: SonarQube",
          "match": "<mark>Sonar</mark>Source :: SonarQube"
        },
        {
          "organization": "default-organization",
          "key": "org.sonarsource:sonarlint",
          "name": "SonarSource :: SonarLint",
          "match": "<mark>Sonar</mark>Source :: SonarLint"
        }
      ],
      "more": 74
    },
    {
      "category": "files",
      "items": [
      ]
    }
  ],
  "organizations": [
    {
      "key": "default-organization",
      "name": "Default Organization"
    }
  ],
  "warning": "short_input"
}
