{
  "paging": {
    "pageIndex": 1,
    "pageSize": 100,
    "total": 3
  },
  "baseComponent": {
    "organization": "my-org-1",
    "id": "MY_PROJECT_ID",
    "key": "MY_PROJECT_KEY",
    "name": "Project Name",
    "qualifier": "TRK"
  },
  "components": [
    {
      "organization": "my-org-1",
      "id": "AVHE6Jo2EplJjXTo0Rzw",
      "key": "com.sonarsource:java-markdown:src/test/java/com/sonarsource/markdown/BasicMarkdownParser.java",
      "name": "BasicMarkdownParser.java",
      "qualifier": "UTS",
      "path": "src/test/java/com/sonarsource/markdown/BasicMarkdownParser.java",
      "language":"java"
    },
    {
      "organization": "my-org-1",
      "id": "AVHE6Jo3EplJjXTo0Rzx",
      "key": "com.sonarsource:java-markdown:src/test/java/com/sonarsource/markdown/BasicMarkdownParserTest.java",
      "name": "BasicMarkdownParserTest.java",
      "qualifier": "UTS",
      "path": "src/test/java/com/sonarsource/markdown/BasicMarkdownParserTest.java",
      "language":"java"
    },
    {
      "organization": "my-org-1",
      "id": "AVHE6Jo1EplJjXTo0Rzj",
      "key": "com.sonarsource:java-markdown:src/main/java/com/sonarsource/markdown",
      "name": "src/main/java/com/sonarsource/markdown",
      "qualifier": "DIR",
      "path": "src/main/java/com/sonarsource/markdown"
    }
  ]
}
